Workbook

Sheet NAsource
A1: Amazon (AMZN) stock prices May 1997 - November 2017.
A2: Downloaded from finance.yahoo.com.

Sheet Table
A1: Date | B1: Open | C1: High | D1: Low | E1: Close | F1: Volume | G1: Adj Close | H1: Daily Range | I1: Daily Range % | J1: Daily Change | K1: Daily Change % | L1: Adjustment ratio | M1: Adjusted High Price | N1: Adjusted Low price | O1: Adj. Close Change since first day | P1: Adj. Close change percentage since first day
A2: 43054 | B2: 1127.01 | C2: 1131.75 | D2: 1121.63 | E2: 1126.69 | F2: 3905400 | G2: 1126.69 | H2: =C2-D2 -> 10.12 | I2: =(C2-D2)/D2 -> 0.0090225832 | J2: =G2-G3 -> -10.15 | K2: =(G2-G3)/G3 -> -0.0089282573 | L2: =G2/E2 -> 1 | M2: =L2*C2 -> 1131.75 | N2: =L2*D2 -> 1121.63 | O2: =G2-$G$5163 -> 1124.73 | P2: =(G2-$G$5163)/$G$5163 -> 573.84184
A3: 43053 | B3: 1130.11 | C3: 1138 | D3: 1123.89 | E3: 1136.84 | F3: 3138400 | G3: 1136.84 | H3: =C3-D3 -> 14.11 | I3: =(C3-D3)/D3 -> 0.012554609 | J3: =G3-G4 -> 7.67 | K3: =(G3-G4)/G4 -> 0.0067925999 | L3: =G3/E3 -> 1 | M3: =L3*C3 -> 1138 | N3: =L3*D3 -> 1123.89 | O3: =G3-$G$5163 -> 1134.88 | P3: =(G3-$G$5163)/$G$5163 -> 579.02041
A4: 43052 | B4: 1123 | C4: 1139.9 | D4: 1122.34 | E4: 1129.17 | F4: 2918400 | G4: 1129.17 | H4: =C4-D4 -> 17.56 | I4: =(C4-D4)/D4 -> 0.015645883 | J4: =G4-G5 -> 3.82 | K4: =(G4-G5)/G5 -> 0.0033944995 | L4: =G4/E4 -> 1 | M4: =L4*C4 -> 1139.9 | N4: =L4*D4 -> 1122.34 | O4: =G4-$G$5163 -> 1127.21 | P4: =(G4-$G$5163)/$G$5163 -> 575.10714
A5: 43049 | B5: 1126.1 | C5: 1131.75 | D5: 1124.06 | E5: 1125.35 | F5: 2179900 | G5: 1125.35 | H5: =C5-D5 -> 7.69 | I5: =(C5-D5)/D5 -> 0.0068412718 | J5: =G5-G6 -> -3.78 | K5: =(G5-G6)/G6 -> -0.0033477102 | L5: =G5/E5 -> 1 | M5: =L5*C5 -> 1131.75 | N5: =L5*D5 -> 1124.06 | O5: =G5-$G$5163 -> 1123.39 | P5: =(G5-$G$5163)/$G$5163 -> 573.15816
A6: 43048 | B6: 1125.96 | C6: 1129.62 | D6: 1115.77 | E6: 1129.13 | F6: 3732700 | G6: 1129.13 | H6: =C6-D6 -> 13.85 | I6: =(C6-D6)/D6 -> 0.012412952 | J6: =G6-G7 -> -3.75 | K6: =(G6-G7)/G7 -> -0.0033101476 | L6: =G6/E6 -> 1 | M6: =L6*C6 -> 1129.62 | N6: =L6*D6 -> 1115.77 | O6: =G6-$G$5163 -> 1127.17 | P6: =(G6-$G$5163)/$G$5163 -> 575.08673
A7: 43047 | B7: 1122.82 | C7: 1135.54 | D7: 1119.11 | E7: 1132.88 | F7: 2581500 | G7: 1132.88 | H7: =C7-D7 -> 16.43 | I7: =(C7-D7)/D7 -> 0.014681309 | J7: =G7-G8 -> 9.71 | K7: =(G7-G8)/G8 -> 0.0086451739 | L7: =G7/E7 -> 1 | M7: =L7*C7 -> 1135.54 | N7: =L7*D7 -> 1119.11 | O7: =G7-$G$5163 -> 1130.92 | P7: =(G7-$G$5163)/$G$5163 -> 577
A8: 43046 | B8: 1124.74 | C8: 1130.6 | D8: 1117.5 | E8: 1123.17 | F8: 2689000 | G8: 1123.17 | H8: =C8-D8 -> 13.1 | I8: =(C8-D8)/D8 -> 0.011722595 | J8: =G8-G9 -> 2.51 | K8: =(G8-G9)/G9 -> 0.0022397516 | L8: =G8/E8 -> 1 | M8: =L8*C8 -> 1130.6 | N8: =L8*D8 -> 1117.5 | O8: =G8-$G$5163 -> 1121.21 | P8: =(G8-$G$5163)/$G$5163 -> 572.04592
A9: 43045 | B9: 1109.15 | C9: 1125.41 | D9: 1108.77 | E9: 1120.66 | F9: 3381100 | G9: 1120.66 | H9: =C9-D9 -> 16.64 | I9: =(C9-D9)/D9 -> 0.015007621 | J9: =G9-G10 -> 9.06 | K9: =(G9-G10)/G10 -> 0.0081504138 | L9: =G9/E9 -> 1 | M9: =L9*C9 -> 1125.41 | N9: =L9*D9 -> 1108.77 | O9: =G9-$G$5163 -> 1118.7 | P9: =(G9-$G$5163)/$G$5163 -> 570.76531
A10: 43042 | B10: 1091.15 | C10: 1112.68 | D10: 1088.52 | E10: 1111.6 | F10: 3751500 | G10: 1111.6 | H10: =C10-D10 -> 24.16 | I10: =(C10-D10)/D10 -> 0.022195274 | J10: =G10-G11 -> 17.38 | K10: =(G10-G11)/G11 -> 0.01588346 | L10: =G10/E10 -> 1 | M10: =L10*C10 -> 1112.68 | N10: =L10*D10 -> 1088.52 | O10: =G10-$G$5163 -> 1109.64 | P10: =(G10-$G$5163)/$G$5163 -> 566.14286
A11: 43041 | B11: 1097.81 | C11: 1101.94 | D11: 1086.87 | E11: 1094.22 | F11: 3684900 | G11: 1094.22 | H11: =C11-D11 -> 15.07 | I11: =(C11-D11)/D11 -> 0.013865504 | J11: =G11-G12 -> -9.46 | K11: =(G11-G12)/G12 -> -0.008571325 | L11: =G11/E11 -> 1 | M11: =L11*C11 -> 1101.94 | N11: =L11*D11 -> 1086.87 | O11: =G11-$G$5163 -> 1092.26 | P11: =(G11-$G$5163)/$G$5163 -> 557.27551
A12: 43040 | B12: 1105.4 | C12: 1108.97 | D12: 1096.74 | E12: 1103.68 | F12: 3755500 | G12: 1103.68 | H12: =C12-D12 -> 12.23 | I12: =(C12-D12)/D12 -> 0.01115123 | J12: =G12-G13 -> -1.6 | K12: =(G12-G13)/G13 -> -0.001447597 | L12: =G12/E12 -> 1 | M12: =L12*C12 -> 1108.97 | N12: =L12*D12 -> 1096.74 | O12: =G12-$G$5163 -> 1101.72 | P12: =(G12-$G$5163)/$G$5163 -> 562.10204
A13: 43039 | B13: 1109 | C13: 1110.54 | D13: 1101.12 | E13: 1105.28 | F13: 3477000 | G13: 1105.28 | H13: =C13-D13 -> 9.42 | I13: =(C13-D13)/D13 -> 0.0085549259 | J13: =G13-G14 -> -5.57 | K13: =(G13-G14)/G14 -> -0.0050141783 | L13: =G13/E13 -> 1 | M13: =L13*C13 -> 1110.54 | N13: =L13*D13 -> 1101.12 | O13: =G13-$G$5163 -> 1103.32 | P13: =(G13-$G$5163)/$G$5163 -> 562.91837
... A5162: 35566 | B5162: 23.63 | C5162: 23.75 | D5162: 20.51 | E5162: 20.75 | F5162: 14700000 | G5162: 1.73 | H5162: =C5162-D5162 -> 3.24 | I5162: =(C5162-D5162)/D5162 -> 0.15797172 | J5162: =G5162-G5163 -> -0.23 | K5162: =(G5162-G5163)/G5163 -> -0.11734694 | L5162: =G5162/E5162 -> 0.083373494 | M5162: =L5162*C5162 -> 1.9801205 | N5162: =L5162*D5162 -> 1.7099904 | O5162: =G5162-$G$5163 -> -0.23 | P5162: =(G5162-$G$5163)/$G$5163 -> -0.11734694
A5163: 35565 | B5163: 29.26 | C5163: 29.97 | D5163: 23.14 | E5163: 23.5 | F5163: 72156000 | G5163: 1.96 | H5163: =C5163-D5163 -> 6.83 | I5163: =(C5163-D5163)/D5163 -> 0.2951599 | L5163: =G5163/E5163 -> 0.083404255 | M5163: =L5163*C5163 -> 2.4996255 | N5163: =L5163*D5163 -> 1.9299745 | O5163: =G5163-$G$5163 -> 0 | P5163: =(G5163-$G$5163)/$G$5163 -> 0

Sheet Amazon Stock Price Analysis
A1: Part 1:
B2: Daily Range
A3: Date | B3: High | C3: Low | D3: Daily Range | E3: Daily Range % | F3: Adj.Close | G3: Adj Close previous day | H3: Daily Change | I3: Daily C
A4: 42117 | B4: =_xlfn.XLOOKUP(A4,Table!A:A, Table!C:C) -> 391.88 | C4: =_xlfn.XLOOKUP(A4,Table!A:A, Table!D:D) -> 386.15 | D4: =B4-C4 -> 5.73 | E4: =(B4-C4)/C4 -> 0.014838793 | F4: =_xlfn.XLOOKUP(A4,Table!A:A, Table!G:G) -> 389.99
A5: 42151 | B5: =_xlfn.XLOOKUP(A5,Table!A:A, Table!C:C) -> 431.85 | C5: =_xlfn.XLOOKUP(A5,Table!A:A, Table!D:D) -> 425.01 | D5: =B5-C5 -> 6.84 | E5: =(B5-C5)/C5 -> 0.016093739 | F5: =_xlfn.XLOOKUP(A5,Table!A:A, Table!G:G) -> 431.42
A6: 42446 | B6: =_xlfn.XLOOKUP(A6,Table!A:A, Table!C:C) -> 571.4 | C6: =_xlfn.XLOOKUP(A6,Table!A:A, Table!D:D) -> 555.01 | D6: =B6-C6 -> 16.39 | E6: =(B6-C6)/C6 -> 0.029530999 | F6: =_xlfn.XLOOKUP(A6,Table!A:A, Table!G:G) -> 559.44 | G6: =_xlfn.XLOOKUP(A9, Table!A:A, Table!G:G) -> 574.27 | H6: =F6-G6 -> -14.83
A7: 41796
C8: #3a. | D8: #4a. | F8: #5
A9: 42445 | C9: =_xlfn.XLOOKUP(A6, Table!A:A, Table!J:J) -> -14.83 | D9: =_xlfn.XLOOKUP(A7, Table!A:A, Table!K:K) -> 0.01885218 | F9: Daily Range | G9: Daily Range % | H9: Daily Change | I9: Daily Change %
E10: Largest | F10: =MAX(Table!H:H) -> 85.99 | G10: =MAX(Table!I:I) -> 0.33328202 | H10: =MAX(Table!J:J) -> 128.52 | I10: =MAX(Table!K:K) -> 0.34471366
A11: Average Growth Rate | F11: =_xlfn.XLOOKUP(F10,Table!H:H, Table!$A:$A) -> 42895 | G11: =_xlfn.XLOOKUP(G10,Table!I:I, Table!$A:$A) -> 36039 | H11: =_xlfn.XLOOKUP(H10,Table!J:J, Table!$A:$A) -> 43035 | I11: =_xlfn.XLOOKUP(I10,Table!K:K, Table!$A:$A) -> 37221
A12: Present Value, P | B12: 3480 | C12: 9971.25 | E12: Smallest | F12: =MIN(Table!H:H) -> 0.12 | G12: =MIN(Table!I:I) -> 0.0037501176 | H12: =MIN(Table!J:J) -> -48.35 | I12: =MIN(Table!K:K) -> -0.24766064
A13: Future Value, f(t) | B13: 4242.1 | C13: 25784.96 | F13: =_xlfn.XLOOKUP(F12,Table!H:H, Table!$A:$A) -> 35607 | G13: =_xlfn.XLOOKUP(G12,Table!I:I, Table!$A:$A) -> 42811 | H13: =_xlfn.XLOOKUP(H12,Table!J:J, Table!$A:$A) -> 42398 | I13: =_xlfn.XLOOKUP(I12,Table!K:K, Table!$A:$A) -> 37096
A14: time (years), t | B14: 10 | C14: 3.5
A15: CAGR, r | B15: =(B13/B12)^(1/B14)-1 -> 0.019999986 | C15: =(C13/C12)^(1/C14)-1 -> 0.31186918 | F15: 20000
A16: Xlookup | F16: =F15+F15*0.025 -> 20500 | H16: #6, #7, #8,#9
A17: Find the Close and Adj. Close on 12/22/14 | F17: =F16+F16*0.025 -> 21012.5 | H17: Criteria | I17: # of days | J17: %
A18: Date | B18: Close | C18: Adj.Close | F18: =F17+F17*0.025 -> 21537.812 | H18: <0 | I18: =COUNTIF(Table!K:K, H18) -> 2539 | J18: =I18/I21 -> 0.49195892
A19: 41995 | B19: =_xlfn.XLOOKUP(A19,Table!A:A,Table!E:E) -> 306.54 | C19: =_xlfn.XLOOKUP(A19,Table!A:A, Table!G:G ) -> 306.54 | F19: =F18+F18*0.025 -> 22076.258 | H19: >0 | I19: =COUNTIF(Table!K:K, H19) -> 2587 | J19: =I19/I21 -> 0.50125945
F20: =F19+F19*0.025 -> 22628.164 | H20: >=2.00% | I20: =COUNTIF(Table!K:K, $H$20) -> 1055 | J20: =I20/I21 -> 0.20441775
A21: Find all data for the given date. | H21: >2.00% | I21: 5161 | J21: =J19+J18 -> 0.99321837
A22: Date | B22: Open | C22: High | D22: Low | E22: Close | F22: Volume | G22: Adj.Close | H22: < 8000000 | I22: =COUNTIFS(Table!K:K, H21, Table!F:F, H22) -> 488 | J22: =I22/I21 -> 0.094555319
A23: 41995 | B23: {=_xlfn.XLOOKUP(A23,Table!A:A, Table!B:G)} -> 301.94 | C23: 307.36 | D23: 301.94 | E23: 306.54 | F23: 4003800 | G23: 306.54
A24: 4/23/
A26: Percent Change | H26: Part 3
A27: (New-Old)/Old | H27: #1-#4
C28: =2.48- (2.48*0.1009) -> 2.229768 | G28: Date | H28: Adjustment ratio | I28: Adj High | J28: Adj. Low
A29: =(1.19-1.683)/1.683 -> -0.29292929 | G29: 36395 | H29: =_xlfn.XLOOKUP(G29, Table!A:A, Table!L:L) -> 0.5
A30: =(66-54)/54 -> 0.22222222 | G30: 36896 | H30: =_xlfn.XLOOKUP(G30, Table!A:A, Table!L:L) -> 1
B31: Round, Rounddown, and Roundup | E31: Int | G31: 42433 | H31: =_xlfn.XLOOKUP(G31, Table!A:A, Table!L:L) -> 1
A32: Number | B32: Whole | C32: Nereast cent | G32: 35663 | I32: =_xlfn.XLOOKUP(G32, Table!A:A, Table!M:M) -> 2.1698582
A33: 2.67 | B33: =ROUND(A33,0) -> 3 | C33: =ROUND(A33,2) -> 2.67 | E33: =INT(A33) -> 2 | G33: 36348 | I33: =_xlfn.XLOOKUP(G33, Table!A:A, Table!M:M) -> 63.75
A34: 7.8949 | B34: =ROUND(A34,0) -> 8 | C34: =ROUND(A34,2) -> 7.89
A35: 13.7 | B35: =ROUND(A35,0) -> 14 | C35: =ROUND(A35,2) -> 13.7
A36: 15.2229 | B36: =ROUND(A36,0) -> 15 | C36: =ROUND(A36,2) -> 15.22 | G36: Homework #2
F37: Criteria | G37: Date
A38: "Tuition costs were 24.97% higher in 2020 compared to 2015. In 2020 the tuition cost was $10,502. What was the tuition cost in 2015?" | G38: 42880 | H38: =_xlfn.XLOOKUP(G38,Table!A:A, Table!I:I) -> 0.017197666
A39: =10502/1.2497 -> 8403.6169 | B39: <-Answer | G39: 42821 | H39: =_xlfn.XLOOKUP(G39, Table!A:A, Table!J:J) -> 1.21
F40: >4.58% | H40: =COUNTIF(Table!$K:$K, F40) -> 386
F41: <3.368 | H41: =COUNTIF(Table!H:H, F41) -> 2558
G42: 36278 | H42: =_xlfn.XLOOKUP(G42, Table!A:A, Table!M:M) -> 101
A44: date | B44: Homework #3 | F44: Part 6 | G44: #1
A45: 42564 | B45: =_xlfn.XLOOKUP(A45, Table!A:A, Table!O:O) -> 740.67 | C45: #1 | G45: Date | H45: close | I45: % change in adj.close
G46: 37621 | H46: 18.89 | I46: 863.77551 | J46: =27390.5+236592.43 -> 263982.93
A47: 35885 | B47: =_xlfn.XLOOKUP(A47, Table!A:A, Table!P:P) -> 2.6377551 | C47: #2
A48: 35971 | B48: =_xlfn.XLOOKUP(A48, Table!A:A, Table!P:P) -> 7.4234694
A50: 37340 | B50: =_xlfn.XLOOKUP(A50, Table!A:A, Table!P:P) -> 6.5204082
A51: 37426 | B51: =_xlfn.XLOOKUP(A51, Table!A:A, Table!P:P) -> 8.3367347 | F51: Part 5
G52: Date | H52: Adjusted Close | I52: $ Change from 1st trading day | J52: %Change=(new-old)/old
A53: 35835 | B53: =_xlfn.XLOOKUP(A53, Table!A:A, Table!P:P) -> 1.4744898 | C53: #3 | F53: 1st Trading Day | G53: 35565 | H53: 1.96
F54: Last Trading Day | G54: 43054 | H54: 1126.69 | I54: =H54-H$53 -> 1124.73 | J54: =(H54-H$53)/H$53 -> 573.84184
G55: 35797 | H55: =_xlfn.XLOOKUP(G55,Table!A:A, Table!G:G) -> 4.96 | I55: =H55-H$53 -> 3 | J55: =(H55-H$53)/H$53 -> 1.5306122 | M55: Amount Available | N55: Buy Date | O55: Close | P55: Shares Bought | Q55: Amount Spent | R55: Unspent
C56: #4 | G56: 36528 | H56: =_xlfn.XLOOKUP(G56,Table!A:A, Table!G:G) -> 89.38 | I56: =H56-H$53 -> 87.42 | J56: =(H56-H$53)/H$53 -> 44.602041 | M56: 4793 | N56: 36893 | O56: =_xlfn.XLOOKUP(N56, Table!A:A, Table!E:E) -> 13.88 | P56: =ROUNDDOWN(M56/O56,0) -> 345 | Q56: =P56*O56 -> 4788.6 | R56: =M56-Q56 -> 4.4
A57: Date | B57: Close Price | G57: 37258 | H57: =_xlfn.XLOOKUP(G57,Table!A:A, Table!G:G) -> 10.96 | I57: =H57-H$53 -> 9 | J57: =(H57-H$53)/H$53 -> 4.5918367
A58: 35565 | B58: 23.5 | G58: 38355 | H58: =_xlfn.XLOOKUP(G58,Table!A:A, Table!G:G) -> 44.52 | I58: =H58-H$53 -> 42.56 | J58: =(H58-H$53)/H$53 -> 21.714286
A59: 37621 | B59: =_xlfn.XLOOKUP(A59, Table!A:A, Table!E:E) -> 18.89 | F59: #4
F60: Amount Available | G60: Buy Date | H60: Close Price | I60: Shares Bought | J60: Amount Spent | K60: Unspent
F61: 25000 | G61: 35565 | H61: 23.5 | I61: =ROUNDDOWN(F61/H61,0) -> 1063 | J61: =I61*H61 -> 24980.5 | K61: =F61-J61 -> 19.5
F63: Adjusted Close on Buy date | G63: Date | H63: Adj.Close | I63: Adjusted Close % | J63: Net gain/loss | K63: Value of Investment
F64: Purchase Date | G64: 35555 | H64: 1.96 | L64: Value of Investment=Amount Spent*(1+Adj Close % on Sell Date)
F65: Sell Date | G65: 35797 | H65: =H55 -> 4.96 | I65: =(H65-$H$64)/$H$64 -> 1.5306122 | J65: =K65-$J$61 -> 38235.459 | K65: =$J$61*(1+I65) -> 63215.959 | L65: Adj.Close %=(new-old)/old
G66: 36528 | H66: =H56 -> 89.38 | I66: =(H66-$H$64)/$H$64 -> 44.602041 | J66: =K66-$J$61 -> 1114181.3 | K66: =$J$61*(1+I66) -> 1139161.8
G67: 37258 | H67: =H57 -> 10.96 | I67: =(H67-$H$64)/$H$64 -> 4.5918367 | J67: =K67-$J$61 -> 114706.38 | K67: =$J$61*(1+I67) -> 139686.88
G68: 38355 | H68: =H58 -> 44.52 | I68: =(H68-$H$64)/$H$64 -> 21.714286 | J68: =K68-$J$61 -> 542433.71 | K68: =$J$61*(1+I68) -> 567414.21
G69: 43054 | H69: 1126.69 | I69: =(H69-$H$64)/$H$64 -> 573.84184 | J69: =K69-$J$61 -> 14334856 | K69: =$J$61*(1+I69) -> 14359837
F71: Part 6
F72: Last Trading Day | G72: 43054 | H72: First Trading Day | J72: 35565
F73: #1
F74: Funds Available | G74: 10000 | H74: Date Purchased | I74: 36528
H75: Close | I75: 89.38
F76: shares purchased | H76: shares purchased | I76: =ROUNDDOWN(G74/I75,0) -> 111
F77: Total Spent | G77: =I75*I76 -> 9921.18
G79: Adj.Close | H79: Difference in adj.close | I79: % Change | J79: Current Value Including Initial Funds | K79: Close on date | L79: Value of Investment on that date
F80: 36528 | G80: =_xlfn.XLOOKUP(F80, Table!A:A, Table!G:G) -> 89.38 | H80: =G80-G$80 -> 0 | I80: =(G80-G$80)/G$80 -> 0 | J80: =G77 -> 9921.18 | K80: =_xlfn.XLOOKUP(F80, Table!A:A, Table!E:E) -> 89.38 | L80: =I$76*K80 -> 9921.18 | M80: Value =Original Purchase* (1+adj.close%)
F81: 37258 | G81: =_xlfn.XLOOKUP(F81, Table!A:A, Table!G:G) -> 10.96 | H81: =G81-G$80 -> -78.42 | I81: =(G81-G$80)/G$80 -> -0.87737749 | J81: =G$77*(1+I81) -> 1216.56 | K81: =_xlfn.XLOOKUP(F81, Table!A:A, Table!E:E) -> 10.96 | L81: =I$76*K81 -> 1216.56 | M81: or
F82: 37988 | G82: =_xlfn.XLOOKUP(F82, Table!A:A, Table!G:G) -> 51.9 | H82: =G82-G$80 -> -37.48 | I82: =(G82-G$80)/G$80 -> -0.41933318 | J82: =G$77*(1+I82) -> 5760.9 | K82: =_xlfn.XLOOKUP(F82, Table!A:A, Table!E:E) -> 51.9 | L82: =I$76*K82 -> 5760.9 | M82: value= # of shares* close on date
F83: 39815 | G83: =_xlfn.XLOOKUP(F83, Table!A:A, Table!G:G) -> 54.36 | H83: =G83-G$80 -> -35.02 | I83: =(G83-G$80)/G$80 -> -0.39181025 | J83: =G$77*(1+I83) -> 6033.96 | K83: =_xlfn.XLOOKUP(F83, Table!A:A, Table!E:E) -> 54.36 | L83: =I$76*K83 -> 6033.96
F84: 43054 | G84: =_xlfn.XLOOKUP(F84, Table!A:A, Table!G:G) -> 1126.69 | H84: =G84-G$80 -> 1037.31 | I84: =(G84-G$80)/G$80 -> 11.605616 | J84: =G$77*(1+I84) -> 125062.59 | K84: =_xlfn.XLOOKUP(F84, Table!A:A, Table!E:E) -> 1126.69 | L84: =I$76*K84 -> 125062.59
F86: Part 7:
E88: 1a. | F88: As of: | G88: Close Price | H88: # new shares just purchased | I88: Total number of shares owned | J88: Amount spent on shares at date | K88: Total spent on shares | L88: Shares Bought | M88: Amount Spent
D89: Money put in | E89: 1000 | F89: 36893 | G89: =_xlfn.XLOOKUP(F89, Table!A:A, Table!E:E) -> 13.88 | H89: =ROUNDDOWN($E$89/G89, 0) -> 72 | I89: =H89 -> 72 | J89: =G89*H89 -> 999.36 | K89: =J89 -> 999.36
F90: 37258 | G90: =_xlfn.XLOOKUP(F90, Table!A:A, Table!E:E) -> 10.96 | H90: =ROUNDDOWN($E$89/G90, 0) -> 91 | I90: =I89+H90 -> 163 | J90: =G90*H90 -> 997.36 | K90: =K89+J90 -> 1996.72
F91: 37623 | G91: =_xlfn.XLOOKUP(F91, Table!A:A, Table!E:E) -> 19.57 | H91: =ROUNDDOWN($E$89/G91, 0) -> 51 | I91: =I90+H91 -> 214 | J91: =G91*H91 -> 998.07 | K91: =K90+J91 -> 2994.79
F92: 37988 | G92: =_xlfn.XLOOKUP(F92, Table!A:A, Table!E:E) -> 51.9 | H92: =ROUNDDOWN($E$89/G92, 0) -> 19 | I92: =I91+H92 -> 233 | J92: =G92*H92 -> 986.1 | K92: =K91+J92 -> 3980.89
F93: 38355 | G93: =_xlfn.XLOOKUP(F93, Table!A:A, Table!E:E) -> 44.52 | H93: =ROUNDDOWN($E$89/G93, 0) -> 22 | I93: =I92+H93 -> 255 | J93: =G93*H93 -> 979.44 | K93: =K92+J93 -> 4960.33
F94: 38720 | G94: =_xlfn.XLOOKUP(F94, Table!A:A, Table!E:E) -> 47.58 | H94: =ROUNDDOWN($E$89/G94, 0) -> 21 | I94: =I93+H94 -> 276 | J94: =G94*H94 -> 999.18 | K94: =K93+J94 -> 5959.51
F95: 39085 | G95: =_xlfn.XLOOKUP(F95, Table!A:A, Table!E:E) -> 38.7 | H95: =ROUNDDOWN($E$89/G95, 0) -> 25 | I95: =I94+H95 -> 301 | J95: =G95*H95 -> 967.5 | K95: =K94+J95 -> 6927.01
F96: 39449 | G96: =_xlfn.XLOOKUP(F96, Table!A:A, Table!E:E) -> 96.25 | H96: =ROUNDDOWN($E$89/G96, 0) -> 10 | I96: =I95+H96 -> 311 | J96: =G96*H96 -> 962.5 | K96: =K95+J96 -> 7889.51
F97: 39815 | G97: =_xlfn.XLOOKUP(F97, Table!A:A, Table!E:E) -> 54.36 | H97: =ROUNDDOWN($E$89/G97, 0) -> 18 | I97: =I96+H97 -> 329 | J97: =G97*H97 -> 978.48 | K97: =K96+J97 -> 8867.99
F98: 40182 | G98: =_xlfn.XLOOKUP(F98, Table!A:A, Table!E:E) -> 133.9 | H98: =ROUNDDOWN($E$89/G98, 0) -> 7 | I98: =I97+H98 -> 336 | J98: =G98*H98 -> 937.3 | K98: =K97+J98 -> 9805.29
F99: 43054 | G99: =_xlfn.XLOOKUP(F99, Table!A:A, Table!E:E) -> 1126.69 | H99: =ROUNDDOWN($E$89/G99, 0) -> 0
E100: 2a. | F100: 37074 | G100: =_xlfn.XLOOKUP(F100, Table!A:A, Table!E:E) -> 14.53 | H100: =ROUNDDOWN($E$89/G100, 0) -> 68 | I100: =H100 -> 68 | J100: =H100*G100 -> 988.04 | K100: =J100 -> 988.04 | L100: 336 | M100: =L100*G100 -> 4882.08
F101: 37438 | G101: =_xlfn.XLOOKUP(F101, Table!A:A, Table!E:E) -> 13.55 | H101: =ROUNDDOWN($E$89/G101, 0) -> 73 | I101: =I100+H101 -> 141 | J101: =H101*G101 -> 989.15 | K101: =K100+J101 -> 1977.19 | L101: 336 | M101: =L101*G101 -> 4552.8
F102: 37803 | G102: =_xlfn.XLOOKUP(F102, Table!A:A, Table!E:E) -> 37.25 | H102: =ROUNDDOWN($E$89/G102, 0) -> 26 | I102: =I101+H102 -> 167 | J102: =H102*G102 -> 968.5 | K102: =K101+J102 -> 2945.69 | L102: 336 | M102: =L102*G102 -> 12516
F103: 38169 | G103: =_xlfn.XLOOKUP(F103, Table!A:A, Table!E:E) -> 52.56 | H103: =ROUNDDOWN($E$89/G103, 0) -> 19 | I103: =I102+H103 -> 186 | J103: =H103*G103 -> 998.64 | K103: =K102+J103 -> 3944.33 | L103: 336 | M103: =L103*G103 -> 17660.16
F104: 38534 | G104: =_xlfn.XLOOKUP(F104, Table!A:A, Table!E:E) -> 32.91 | H104: =ROUNDDOWN($E$89/G104, 0) -> 30 | I104: =I103+H104 -> 216 | J104: =H104*G104 -> 987.3 | K104: =K103+J104 -> 4931.63 | L104: 336 | M104: =L104*G104 -> 11057.76
F105: 38901 | G105: =_xlfn.XLOOKUP(F105, Table!A:A, Table!E:E) -> 38.61 | H105: =ROUNDDOWN($E$89/G105, 0) -> 25 | I105: =I104+H105 -> 241 | J105: =H105*G105 -> 965.25 | K105: =K104+J105 -> 5896.88 | L105: 336 | M105: =L105*G105 -> 12972.96
A106: CAGR=(Adj.new/Adj.Old)^(1/t) -1 | F106: 39265 | G106: =_xlfn.XLOOKUP(F106, Table!A:A, Table!E:E) -> 69.61 | H106: =ROUNDDOWN($E$89/G106, 0) -> 14 | I106: =I105+H106 -> 255 | J106: =H106*G106 -> 974.54 | K106: =K105+J106 -> 6871.42 | L106: 336 | M106: =L106*G106 -> 23388.96
A107: t=(new date-old date)/365.25 | F107: 39630 | G107: =_xlfn.XLOOKUP(F107, Table!A:A, Table!E:E) -> 73.62 | H107: =ROUNDDOWN($E$89/G107, 0) -> 13 | I107: =I106+H107 -> 268 | J107: =H107*G107 -> 957.06 | K107: =K106+J107 -> 7828.48 | L107: 336 | M107: =L107*G107 -> 24736.32
F108: 39995 | G108: =_xlfn.XLOOKUP(F108, Table!A:A, Table!E:E) -> 81.6 | H108: =ROUNDDOWN($E$89/G108, 0) -> 12 | I108: =I107+H108 -> 280 | J108: =H108*G108 -> 979.2 | K108: =K107+J108 -> 8807.68 | L108: 336 | M108: =L108*G108 -> 27417.6
...
