Workbook

Sheet Sales estimates
A2: The values in the cells in this table show the estimated number of units that could be sold if the price point in that column and the service in that row were selected.
A3: Some student entrepreneurs are considering starting a business where parents subscribe to "good-for-you" care packages for their college students.
B4: Monthly Price Point
A5: Service | B5: 50 | C5: 35 | D5: 25 | E5: 15
A6: Shaving and grooming supplies | B6: 1200 | C6: 2000 | D6: 3000 | E6: 4000
A7: Healthy foods: dried goods | B7: 1500 | C7: 1800 | D7: 2500 | E7: 3500
A8: Fresh produce | B8: 2000 | C8: 2500 | D8: 2500 | E8: 2000
A9: Pampering supplies | B9: 500 | C9: 1200 | D9: 3000 | E9: 5000
A10: Room decorations | B10: 400 | C10: 1000 | D10: 3500 | E10: 6000
A14: Part 1: Revenue
A15: Create a revenue table: for each service and each price point, the cell should contain a formula that gives the price for that column times the units for the price and service combination.
A16: Write the formula for cell B19 so that you can drag it right and drag it down without having to change it.
B17: Monthly Price Point
A18: Service | B18: =B5 -> 50 | C18: =C5 -> 35 | D18: =D5 -> 25 | E18: =E5 -> 15
A19: =A6 -> Shaving and grooming supplies | B19: =B$5*B6 -> 60000 | C19: =C$5*C6 -> 70000 | D19: =D$5*D6 -> 75000 | E19: =E$5*E6 -> 60000
A20: =A7 -> Healthy foods: dried goods | B20: =B$5*B7 -> 75000 | C20: =C$5*C7 -> 63000 | D20: =D$5*D7 -> 62500 | E20: =E$5*E7 -> 52500
A21: =A8 -> Fresh produce | B21: =B$5*B8 -> 100000 | C21: =C$5*C8 -> 87500 | D21: =D$5*D8 -> 62500 | E21: =E$5*E8 -> 30000
A22: =A9 -> Pampering supplies | B22: =B$5*B9 -> 25000 | C22: =C$5*C9 -> 42000 | D22: =D$5*D9 -> 75000 | E22: =E$5*E9 -> 75000
A23: =A10 -> Room decorations | B23: =B$5*B10 -> 20000 | C23: =C$5*C10 -> 35000 | D23: =D$5*D10 -> 87500 | E23: =E$5*E10 -> 90000
A25: Part 2: Profit
A26: Using the cost percentage estimates on the next tab, create a profit table: for each service and each price point, the cell should contain a formula that gives profit for that price and service combination.
A27: Write the formula for cell B30 so that you can drag it right and drag it down without having to change it.
B28: Monthly Price Point
A29: Service | B29: =B5 -> 50 | C29: =C5 -> 35 | D29: =D5 -> 25 | E29: =E5 -> 15
A30: =A6 -> Shaving and grooming supplies | B30: =B19-'Cost percentage estimates'!$B2*B$29*B6 -> 24000 | C30: =C19-'Cost percentage estimates'!$B2*C$29*C6 -> 28000 | D30: =D19-'Cost percentage estimates'!$B2*D$29*D6 -> 30000 | E30: =E19-'Cost percentage estimates'!$B2*E$29*E6 -> 24000
A31: =A7 -> Healthy foods: dried goods | B31: =B20-'Cost percentage estimates'!$B3*B$29*B7 -> 33750 | C31: =C20-'Cost percentage estimates'!$B3*C$29*C7 -> 28350 | D31: =D20-'Cost percentage estimates'!$B3*D$29*D7 -> 28125 | E31: =E20-'Cost percentage estimates'!$B3*E$29*E7 -> 23625
A32: =A8 -> Fresh produce | B32: =B21-'Cost percentage estimates'!$B4*B$29*B8 -> 25000 | C32: =C21-'Cost percentage estimates'!$B4*C$29*C8 -> 21875 | D32: =D21-'Cost percentage estimates'!$B4*D$29*D8 -> 15625 | E32: =E21-'Cost percentage estimates'!$B4*E$29*E8 -> 7500
A33: =A9 -> Pampering supplies | B33: =B22-'Cost percentage estimates'!$B5*B$29*B9 -> 10000 | C33: =C22-'Cost percentage estimates'!$B5*C$29*C9 -> 16800 | D33: =D22-'Cost percentage estimates'!$B5*D$29*D9 -> 30000 | E33: =E22-'Cost percentage estimates'!$B5*E$29*E9 -> 30000
A34: =A10 -> Room decorations | B34: =B23-'Cost percentage estimates'!$B6*B$29*B10 -> 10000 | C34: =C23-'Cost percentage estimates'!$B6*C$29*C10 -> 17500 | D34: =D23-'Cost percentage estimates'!$B6*D$29*D10 -> 43750 | E34: =E23-'Cost percentage estimates'!$B6*E$29*E10 -> 45000
A36: Profit margin
B37: Monthly Price Point
A38: Service | B38: =B5 -> 50 | C38: =C5 -> 35 | D38: =D5 -> 25 | E38: =E5 -> 15
A39: =A6 -> Shaving and grooming supplies | B39: =B30/B19 -> 0.4 | C39: =C30/C19 -> 0.4 | D39: =D30/D19 -> 0.4 | E39: =E30/E19 -> 0.4
A40: =A7 -> Healthy foods: dried goods | B40: =B31/B20 -> 0.45 | C40: =C31/C20 -> 0.45 | D40: =D31/D20 -> 0.45 | E40: =E31/E20 -> 0.45
A41: =A8 -> Fresh produce | B41: =B32/B21 -> 0.25 | C41: =C32/C21 -> 0.25 | D41: =D32/D21 -> 0.25 | E41: =E32/E21 -> 0.25
A42: =A9 -> Pampering supplies | B42: =B33/B22 -> 0.4 | C42: =C33/C22 -> 0.4 | D42: =D33/D22 -> 0.4 | E42: =E33/E22 -> 0.4
A43: =A10 -> Room decorations | B43: =B34/B23 -> 0.5 | C43: =C34/C23 -> 0.5 | D43: =D34/D23 -> 0.5 | E43: =E34/E23 -> 0.5

Sheet Cost percentage estimates
A1: Service | B1: Estimated cost of materials, production, and delivery, as a percentage of price charged.
A2: Shaving and grooming supplies | B2: 0.6
A3: Healthy foods: dried goods | B3: 0.55
A4: Fresh produce | B4: 0.75
A5: Pampering supplies | B5: 0.6
A6: Room decorations | B6: 0.5
A9: For example: if the price charged is $25 (per month) and the cost is 60% of the price, the entrepreneurs make $10 in profit (per month) for each subscription.
